nonebot_plugin_mclib-0.0.3.post2.dist-info/METADATA
nonebot_plugin_mclib-0.0.3.post2.dist-info/WHEEL
nonebot_plugin_mclib-0.0.3.post2.dist-info/entry_points.txt
nonebot_plugin_mclib-0.0.3.post2.dist-info/licenses/LICENSE
nonebot_plugin_mclib/__init__.py
nonebot_plugin_mclib/player.py
nonebot_plugin_mclib/server.py
nonebot_plugin_mclib-0.0.3.post2.dist-info/RECORD
