Metadata-Version: 2.1
Name: nonebot_plugin_mclib
Version: 0.0.3.post2
Summary: 我的世界服务器状态查询或正版玩家信息查询插件
Keywords: mc,nonebot
Author-Email: JohnRichard4096 <windowserror@163.com>
License: GPL-3.0-or-later
Project-URL: Homepage, https://github.com/LiteSuggarDEV/nonebot_plugin_mclib/
Project-URL: Source, https://github.com/LiteSuggarDEV/nonebot_plugin_mclib/
Project-URL: Issue Tracker, https://github.com/LiteSuggarDEV/nonebot_plugin_mclib/issues
Requires-Python: <4.0,>=3.9
Requires-Dist: nonebot2>=2.2.0
Requires-Dist: nonebot-adapter-onebot>=2.0.0
Requires-Dist: mcstatus>=11.0.0
Requires-Dist: aiohttp>=3.8.3
